[
  {
    "episode": 4,
    "fileIndex": 1,
    "day": "Viernes",
    "daySlug": "viernes",
    "title": "Para eso he venido",
    "series": "Episodio 4",
    "guide": "https://www.jw.org/es/biblioteca/%C3%ADndices/guia-videos-buenas-noticias-segun-jesus/Para-eso-he-venido-Gu%C3%ADa-de-videos/",
    "scenes": [
      {
        "description": "Jesús enseña en la sinagoga de Capernaúm; expulsa a un demonio",
        "timeStart": "00:00:00.00",
        "timeEnd": "00:02:39.37",
        "references": "Marcos 1:21-29; Lucas 4:31-37",
        "refs": [
          {
            "label": "Mr 1:21-29;",
            "tv": "41001021-41001029",
            "href": "/es/biblioteca/biblia/biblia-estudio/libros/marcos/1/#v41001021-v41001029"
          },
          {
            "label": "Lu 4:31-37",
            "tv": "42004031-42004037",
            "href": "/es/biblioteca/biblia/biblia-estudio/libros/lucas/4/#v42004031-v42004037"
          }
        ],
        "paragraphs": [
          "Y entraron en Capernaúm.",
          "En cuanto comenzó el sábado, él entró en la sinagoga y se puso a enseñar.",
          "La gente quedó impactada con su manera de enseñar, porque les enseñaba como alguien con autoridad, y no como los escribas. Justo en ese momento estaba en la sinagoga de ellos un hombre poseído por un espíritu maligno.",
          "Para que se asombren.",
          "¿Qué tenemos que ver contigo, Jesús el Nazareno? ¿Viniste a destruirnos? Sé perfectamente quién eres: ¡el Santo de Dios! ¡Basta! ¡Cállate y sal de él!",
          "Y el espíritu maligno, después de provocarle convulsiones al hombre y de gritar con todas sus fuerzas, salió de él.",
          "Todos quedaron tan asombrados que empezaron a debatir el asunto entre ellos. Pero ¿qué es esto?",
          "¡Es una nueva forma de enseñar! Hasta a los espíritus malignos les da órdenes con autoridad, y estos lo obedecen. De modo que la fama de Jesús enseguida se extendió en todas direcciones, por toda la región de Galilea. ¡Es un milagro! Luego salieron de la sinagoga y, junto con Santiago y Juan, fueron a la casa de Simón y Andrés."
        ]
      },
      {
        "description": "Jesús cura a la suegra de Pedro",
        "timeStart": "00:02:56.22",
        "timeEnd": "00:05:10.64",
        "references": "Lucas 4:38, 39; Mateo 8:14, 15; Marcos 1:30, 31",
        "refs": [
          {
            "label": "Lu 4:38, 39;",
            "tv": "42004038-42004039",
            "href": "/es/biblioteca/biblia/biblia-estudio/libros/lucas/4/#v42004038-v42004039"
          },
          {
            "label": "Mt 8:14, 15;",
            "tv": "40008014-40008015",
            "href": "/es/biblioteca/biblia/biblia-estudio/libros/mateo/8/#v40008014-v40008015"
          },
          {
            "label": "Mr 1:30, 31",
            "tv": "41001030-41001031",
            "href": "/es/biblioteca/biblia/biblia-estudio/libros/marcos/1/#v41001030-v41001031"
          }
        ],
        "paragraphs": [
          "Y resulta que la suegra de Simón tenía una fiebre muy alta, y le pidieron que la ayudara.",
          "Así que se inclinó sobre ella.",
          "—Fiebre...",
          "—Y reprendió a la fiebre. … sal de ella.",
          "Y la fiebre se le fue. Al instante ella se levantó y se puso a atenderlos."
        ]
      },
      {
        "description": "Jesús cura a muchos otros",
        "timeStart": "00:05:12.48",
        "timeEnd": "00:07:21.86",
        "references": "Lucas 4:40, 41; Mateo 8:16, 17; Marcos 1:32-34",
        "refs": [
          {
            "label": "Lu 4:40, 41;",
            "tv": "42004040-42004041",
            "href": "/es/biblioteca/biblia/biblia-estudio/libros/lucas/4/#v42004040-v42004041"
          },
          {
            "label": "Mt 8:16, 17;",
            "tv": "40008016-40008017",
            "href": "/es/biblioteca/biblia/biblia-estudio/libros/mateo/8/#v40008016-v40008017"
          },
          {
            "label": "Mr 1:32-34",
            "tv": "41001032-41001034",
            "href": "/es/biblioteca/biblia/biblia-estudio/libros/marcos/1/#v41001032-v41001034"
          }
        ],
        "paragraphs": [
          "Cuando se estaba poniendo el sol, todos los que tenían enfermos, con diferentes enfermedades, se los llevaron a él.",
          "Rabí. Maestro. ¡Por favor, acércate, Rabí! ¡Maestro, ayúdanos, por favor!",
          "Y él los curó poniendo las manos sobre cada uno de ellos. Esto pasó para que se cumpliera lo que se había dicho por medio del profeta Isaías: “Él mismo tomó nuestras enfermedades y cargó con nuestras dolencias”.",
          "También de mucha gente salían demonios gritando: ¡Tú eres el Hijo de Dios! Cállate y sal de él. Pero él los reprendía y no los dejaba hablar porque ellos sabían que él era el Cristo."
        ]
      },
      {
        "description": "Jesús ora en un lugar solitario",
        "timeStart": "00:07:25.07",
        "timeEnd": "00:09:47.71",
        "references": "Marcos 1:35-38; Lucas 4:42, 43",
        "refs": [
          {
            "label": "Mr 1:35-38;",
            "tv": "41001035-41001038",
            "href": "/es/biblioteca/biblia/biblia-estudio/libros/marcos/1/#v41001035-v41001038"
          },
          {
            "label": "Lu 4:42, 43",
            "tv": "42004042-42004043",
            "href": "/es/biblioteca/biblia/biblia-estudio/libros/lucas/4/#v42004042-v42004043"
          }
        ],
        "paragraphs": [
          "Temprano por la mañana, mientras todavía estaba oscuro, se levantó y salió; se fue a un lugar solitario y allí se puso a orar.",
          "—Maestro.",
          "—Sal, por favor.",
          "—Por favor, sal.",
          "—Por favor. Maestro. ¿Dónde está el Maestro? ¿Dónde está?",
          "—¿Dónde está el Maestro?",
          "—Maestro. ¡Por favor! ¿Dónde está el Maestro? Por favor.",
          "¿Dónde está?",
          "Pero Simón y los que estaban con él salieron a buscarlo por todos lados, y lo encontraron.",
          "Todos te están buscando.",
          "Vámonos a otra parte, a los pueblos vecinos, para que también predique allí, porque para eso he venido."
        ]
      },
      {
        "description": "Jesús predica, enseña y cura a la gente",
        "timeStart": "00:09:48.88",
        "timeEnd": "00:13:54.17",
        "references": "Mateo 4:23-25; Marcos 1:39",
        "refs": [
          {
            "label": "Mt 4:23-25;",
            "tv": "40004023-40004025",
            "href": "/es/biblioteca/biblia/biblia-estudio/libros/mateo/4/#v40004023-v40004025"
          },
          {
            "label": "Mr 1:39",
            "tv": "41001039",
            "href": "/es/biblioteca/biblia/biblia-estudio/libros/marcos/1/#v41001039"
          }
        ],
        "paragraphs": [
          "Jesús fue por toda Galilea enseñando en las sinagogas de ellos y predicando las buenas noticias del Reino.",
          "Y curaba a la gente de todo tipo de enfermedades y todo tipo de dolencias.",
          "Su fama se extendió por toda Siria. Le traían a todos los que sufrían enfermedades y fuertes dolores, a los endemoniados, a los epilépticos y a los paralíticos.",
          "Y él los curaba.",
          "¡Salgan de ella!",
          "Ya eres libre.",
          "Por eso lo seguían grandes multitudes de Galilea y de la Decápolis, así como de Jerusalén y Judea y de la región al otro lado del Jordán."
        ]
      },
      {
        "description": "Jesús cura a un leproso",
        "timeStart": "00:14:00.30",
        "timeEnd": "00:17:12.91",
        "references": "Marcos 1:40-45; Mateo 8:1-4; Lucas 5:12-15",
        "refs": [
          {
            "label": "Mr 1:40-45;",
            "tv": "41001040-41001045",
            "href": "/es/biblioteca/biblia/biblia-estudio/libros/marcos/1/#v41001040-v41001045"
          },
          {
            "label": "Mt 8:1-4;",
            "tv": "40008001-40008004",
            "href": "/es/biblioteca/biblia/biblia-estudio/libros/mateo/8/#v40008001-v40008004"
          },
          {
            "label": "Lu 5:12-15",
            "tv": "42005012-42005015",
            "href": "/es/biblioteca/biblia/biblia-estudio/libros/lucas/5/#v42005012-v42005015"
          }
        ],
        "paragraphs": [
          "¡Un leproso! ¿Qué? ¿Qué dices? ¡Leproso!",
          "—¡Vete de aquí!",
          "—¡Leproso! ¡No te acerques!",
          "—¡Vete!",
          "—¡Leproso!",
          "—¡Fuera!",
          "—¡Aléjate!",
          "Un leproso se le acercó suplicándole hasta de rodillas. Yo sé que si tú quieres me puedes limpiar.",
          "Jesús se conmovió tanto que extendió la mano y lo tocó.",
          "Yo quiero.",
          "Queda limpio.",
          "Enseguida la lepra desapareció y él quedó limpio.",
          "Entonces Jesús le mandó que se fuera, justo después de ordenarle con firmeza: Cuidado con decirle nada a nadie. Eso sí, vete a presentarte ante el sacerdote y lleva por tu purificación las cosas que Moisés indicó, para que les sirva de testimonio. Pero, después de irse, el hombre se puso a proclamar lo que había pasado y a divulgarlo por todas partes. Así que Jesús ya no podía entrar libremente en ninguna ciudad. Se quedaba a las afueras, en lugares retirados, y aun así la gente seguía viniendo de todos lados a verlo."
        ]
      },
      {
        "description": "Jesús busca un lugar solitario para orar",
        "timeStart": "00:17:12.95",
        "timeEnd": "00:17:26.34",
        "references": "Lucas 5:16",
        "refs": [
          {
            "label": "Lu 5:16",
            "tv": "42005016",
            "href": "/es/biblioteca/biblia/biblia-estudio/libros/lucas/5/#v42005016"
          }
        ],
        "paragraphs": [
          "Él, por su parte, a menudo se iba a orar a lugares retirados."
        ]
      },
      {
        "description": "Jesús perdona y cura a un paralítico en Capernaúm",
        "timeStart": "00:17:26.38",
        "timeEnd": "00:22:28.97",
        "references": "Marcos 2:1-12; Mateo 9:1-8; Lucas 5:17-26",
        "refs": [
          {
            "label": "Mr 2:1-12;",
            "tv": "41002001-41002012",
            "href": "/es/biblioteca/biblia/biblia-estudio/libros/marcos/2/#v41002001-v41002012"
          },
          {
            "label": "Mt 9:1-8;",
            "tv": "40009001-40009008",
            "href": "/es/biblioteca/biblia/biblia-estudio/libros/mateo/9/#v40009001-v40009008"
          },
          {
            "label": "Lu 5:17-26",
            "tv": "42005017-42005026",
            "href": "/es/biblioteca/biblia/biblia-estudio/libros/lucas/5/#v42005017-v42005026"
          }
        ],
        "paragraphs": [
          "Algunos días más tarde, Jesús volvió a entrar en Capernaúm, y corrió la voz de que estaba en casa. Así que muchos se juntaron allí, tantos que no cabía ni uno más, ni siquiera a la entrada. Y él se puso a predicarles el mensaje.",
          "Entonces le trajeron a un paralítico, al que cargaban entre cuatro hombres.",
          "Pero, como había allí una multitud, no pudieron entrar con él hasta donde estaba Jesús.",
          "De verdad les aseguro que viene la hora",
          "—de hecho, ha llegado ya— en que los muertos oirán la voz del Hijo de…, oirán la voz…",
          "Así que quitaron parte del techo justo encima de él, hicieron una abertura y bajaron la camilla en la que estaba acostado el paralítico. Suéltenlo.",
          "Cuando Jesús vio la fe que tenían, le dijo al paralítico: Hijo, tus pecados quedan perdonados.",
          "Ahora bien, estaban sentados allí algunos escribas que razonaban en su corazón: ¿Por qué habla así este hombre? Está blasfemando. ¿Quién puede perdonar pecados aparte de Dios? Jesús, que enseguida se dio cuenta de que estaban razonando de ese modo entre ellos, les dijo: ¿Por qué están razonando eso en su corazón?",
          "¿Qué es más fácil? ¿Decirle al paralítico “tus pecados quedan perdonados”, o decirle “levántate, recoge tu camilla y anda”?",
          "Pero para que vean que el Hijo del Hombre tiene autoridad para perdonar pecados en la tierra...",
          "Yo te digo: levántate, recoge tu camilla y vete a tu casa.",
          "Al instante, y delante de todos, el hombre se levantó, recogió su camilla y salió caminando.",
          "Todos quedaron asombrados y glorificaron a Dios, y decían: “Nunca hemos visto algo así”."
        ]
      },
      {
        "description": "Jesús invita a Mateo a ser su seguidor",
        "timeStart": "00:22:30.64",
        "timeEnd": "00:24:15.79",
        "references": "Marcos 2:13, 14; Mateo 9:9; Lucas 5:27-28",
        "refs": [
          {
            "label": "Mr 2:13, 14;",
            "tv": "41002013-41002014",
            "href": "/es/biblioteca/biblia/biblia-estudio/libros/marcos/2/#v41002013-v41002014"
          },
          {
            "label": "Mt 9:9;",
            "tv": "40009009",
            "href": "/es/biblioteca/biblia/biblia-estudio/libros/mateo/9/#v40009009"
          },
          {
            "label": "Lu 5:27-28",
            "tv": "42005027-42005028",
            "href": "/es/biblioteca/biblia/biblia-estudio/libros/lucas/5/#v42005027-v42005028"
          }
        ],
        "paragraphs": [
          "Una vez más, Jesús se fue a la orilla del mar.",
          "Toda la multitud venía a verlo, y él les enseñaba.",
          "Luego, al irse de allí, Jesús vio a un hombre llamado Mateo sentado en la oficina de los impuestos, y le dijo: Sé mi seguidor.",
          "Enseguida Mateo se levantó y lo siguió."
        ]
      },
      {
        "description": "Jesús come con cobradores de impuestos en la casa de Mateo",
        "timeStart": "00:24:16.41",
        "timeEnd": "00:26:26.38",
        "references": "Marcos 2:15-17; Mateo 9:10-13; Lucas 5:29-32",
        "refs": [
          {
            "label": "Mr 2:15-17;",
            "tv": "41002015-41002017",
            "href": "/es/biblioteca/biblia/biblia-estudio/libros/marcos/2/#v41002015-v41002017"
          },
          {
            "label": "Mt 9:10-13;",
            "tv": "40009010-40009013",
            "href": "/es/biblioteca/biblia/biblia-estudio/libros/mateo/9/#v40009010-v40009013"
          },
          {
            "label": "Lu 5:29-32",
            "tv": "42005029-42005032",
            "href": "/es/biblioteca/biblia/biblia-estudio/libros/lucas/5/#v42005029-v42005032"
          }
        ],
        "paragraphs": [
          "Más tarde, Jesús y sus discípulos estuvieron comiendo en su casa.",
          "También estuvieron con ellos en la comida muchos cobradores de impuestos y pecadores.",
          "Y es que muchos de ellos lo seguían.",
          "Pero los escribas que eran fariseos, al ver que Jesús comía con pecadores y cobradores de impuestos, se pusieron a decirles a los discípulos de él: ¿Él come con cobradores de impuestos y pecadores?",
          "Los que están fuertes no necesitan un médico, pero los enfermos sí.",
          "Así que vayan y aprendan lo que significan estas palabras: “Lo que quiero es compasión, no sacrificios”.",
          "No he venido a llamar a justos, sino a pecadores, para que se arrepientan."
        ]
      },
      {
        "description": "Le preguntan sobre el ayuno",
        "timeStart": "00:26:27.50",
        "timeEnd": "00:29:16.50",
        "references": "Mateo 9:14-17; Lucas 5:33-39; Marcos 2:18-22",
        "refs": [
          {
            "label": "Mt 9:14-17;",
            "tv": "40009014-40009017",
            "href": "/es/biblioteca/biblia/biblia-estudio/libros/mateo/9/#v40009014-v40009017"
          },
          {
            "label": "Lu 5:33-39;",
            "tv": "42005033-42005039",
            "href": "/es/biblioteca/biblia/biblia-estudio/libros/lucas/5/#v42005033-v42005039"
          },
          {
            "label": "Mr 2:18-22",
            "tv": "41002018-41002022",
            "href": "/es/biblioteca/biblia/biblia-estudio/libros/marcos/2/#v41002018-v41002022"
          }
        ],
        "paragraphs": [
          "Entonces se le acercaron los discípulos de Juan y le preguntaron: ¿Por qué nosotros y los fariseos tenemos la costumbre de ayunar pero tus discípulos no?",
          "Cuando hay una boda, los amigos del novio no tienen por qué estar de duelo mientras el novio está con ellos, ¿verdad? El que tiene a la novia es el novio. Pero el amigo del novio, cuando está cerca de él y lo escucha, se siente inmensamente feliz al poder oír la voz del novio.",
          "Pero llegará el día en que les quitarán al novio, y entonces sí ayunarán. Nadie cose un parche de tela nueva en un manto viejo, porque la tela nueva, al encogerse, tira de la prenda vieja y la rotura se hace mayor. Ni nadie pone vino nuevo en odres viejos. Si esto se hiciera, el cuero reventaría y el vino se derramaría, y los odres ya no servirían para nada. La gente pone el vino nuevo en odres nuevos, así se conservan las dos cosas.",
          "Después de beber vino añejo, nadie quiere del nuevo, porque dice: “El añejo es bueno”."
        ]
      },
      {
        "description": "Jesús predica en las sinagogas de Judea",
        "timeStart": "00:29:20.68",
        "timeEnd": "00:29:45.07",
        "references": "Lucas 4:44",
        "refs": [
          {
            "label": "Lu 4:44",
            "tv": "42004044",
            "href": "/es/biblioteca/biblia/biblia-estudio/libros/lucas/4/#v42004044"
          }
        ],
        "paragraphs": [
          "Así que siguió predicando por las sinagogas de Judea."
        ]
      },
      {
        "description": "Jesús cura a un enfermo un sábado junto al estanque de Betzata",
        "timeStart": "00:29:46.87",
        "timeEnd": "00:33:21.04",
        "references": "Juan 5:1-9",
        "refs": [
          {
            "label": "Jn 5:1-9",
            "tv": "43005001-43005009",
            "href": "/es/biblioteca/biblia/biblia-estudio/libros/juan/5/#v43005001-v43005009"
          }
        ],
        "paragraphs": [
          "Después de esto hubo una fiesta de los judíos, y Jesús subió a Jerusalén.",
          "Ahora bien, en Jerusalén, junto a la Puerta de las Ovejas, hay un estanque llamado en hebreo Betzata, que tiene cinco pórticos.",
          "En ese lugar estaba recostada una multitud de enfermos, ciegos, cojos y personas que tenían extremidades atrofiadas. Y había allí un hombre que llevaba 38 años enfermo.",
          "Al ver a este hombre allí acostado, y sabiendo que llevaba enfermo mucho tiempo, Jesús le preguntó: ¿Te gustaría ponerte bien?",
          "Señor, no tengo a nadie que me meta en el estanque cuando el agua se agita.",
          "Además, cada vez que voy a entrar, alguien se me adelanta y baja antes que yo.",
          "¡Levántate!",
          "Recoge tu camilla y camina.",
          "Y el hombre enseguida se puso bien, recogió su camilla y comenzó a caminar.",
          "Aquel día era sábado."
        ]
      },
      {
        "description": "Los judíos interrogan al hombre curado por Jesús",
        "timeStart": "00:33:20.08",
        "timeEnd": "00:34:04.29",
        "references": "Juan 5:10-13",
        "refs": [
          {
            "label": "Jn 5:10-13",
            "tv": "43005010-43005013",
            "href": "/es/biblioteca/biblia/biblia-estudio/libros/juan/5/#v43005010-v43005013"
          }
        ],
        "paragraphs": [
          "Así que los judíos se pusieron a decirle al hombre que había sido curado: Hoy es sábado. No te está permitido cargar la camilla. El hombre que me curó me dijo “Recoge tu camilla y camina”. ¿Quién es el hombre que te dijo “Recógela y camina”? Pero el hombre que había sido curado no lo sabía, porque Jesús había desaparecido entre la multitud que estaba allí."
        ]
      },
      {
        "description": "Jesús encuentra en el templo al hombre que curó",
        "timeStart": "00:34:05.59",
        "timeEnd": "00:34:38.37",
        "references": "Juan 5:14, 15",
        "refs": [
          {
            "label": "Jn 5:14, 15",
            "tv": "43005014-43005015",
            "href": "/es/biblioteca/biblia/biblia-estudio/libros/juan/5/#v43005014-v43005015"
          }
        ],
        "paragraphs": [
          "Después de esto, Jesús lo encontró en el templo y le dijo: Mira, te has curado.",
          "Ya no peques más, no sea que te pase algo peor.",
          "El hombre se fue y les dijo a los judíos que era Jesús el que lo había curado."
        ]
      },
      {
        "description": "Jesús habla de la autoridad que le dio su Padre",
        "timeStart": "00:34:38.41",
        "timeEnd": "00:36:36.36",
        "references": "Juan 5:16-24",
        "refs": [
          {
            "label": "Jn 5:16-24",
            "tv": "43005016-43005024",
            "href": "/es/biblioteca/biblia/biblia-estudio/libros/juan/5/#v43005016-v43005024"
          }
        ],
        "paragraphs": [
          "Por eso los judíos perseguían a Jesús, porque hacía estas cosas en sábado.",
          "Mi Padre hasta ahora sigue trabajando, y yo también.",
          "A raíz de eso, los judíos se esforzaron todavía más por matarlo, porque, además de no respetar el sábado, llamaba a Dios su Padre, haciéndose igual a Dios. De verdad les aseguro que el Hijo no puede hacer ni una sola cosa por su cuenta, solo hace lo que le ve hacer al Padre. Porque todas las cosas que hace el Padre, el Hijo también las hace de la misma manera. Porque el Padre quiere al Hijo y le enseña todas las cosas que él mismo hace, y le enseñará obras más grandes que estas para que ustedes se queden asombrados. Porque, al igual que el Padre resucita a los muertos y les da vida, el Hijo también le da vida a quien él quiere dársela.",
          "Porque el Padre no juzga a nadie, sino que le ha confiado la labor de juzgar al Hijo, para que todos honren al Hijo así como honran al Padre. El que no honra al Hijo no honra al Padre, que lo envió.",
          "De verdad les aseguro que el que oye mis palabras y cree en el que me envió tiene vida eterna y no será juzgado, sino que ha pasado de la muerte a la vida."
        ]
      },
      {
        "description": "Los muertos en sentido espiritual que le hagan caso a Jesús vivirán",
        "timeStart": "00:36:36.40",
        "timeEnd": "00:37:11.06",
        "references": "Juan 5:25-27",
        "refs": [
          {
            "label": "Jn 5:25-27",
            "tv": "43005025-43005027",
            "href": "/es/biblioteca/biblia/biblia-estudio/libros/juan/5/#v43005025-v43005027"
          }
        ],
        "paragraphs": [
          "De verdad les aseguro que viene la hora",
          "—de hecho, ha llegado ya— en que los muertos oirán la voz del Hijo de Dios, y los que hayan hecho caso vivirán. Porque, tal como el Padre tiene vida en sí mismo, también le ha concedido al Hijo tener vida en sí mismo. Y le ha dado autoridad para juzgar, porque él es el Hijo del Hombre."
        ]
      },
      {
        "description": "Los muertos que están en las tumbas conmemorativas serán resucitados",
        "timeStart": "00:37:11.10",
        "timeEnd": "00:37:58.19",
        "references": "Juan 5:28-30",
        "refs": [
          {
            "label": "Jn 5:28-30",
            "tv": "43005028-43005030",
            "href": "/es/biblioteca/biblia/biblia-estudio/libros/juan/5/#v43005028-v43005030"
          }
        ],
        "paragraphs": [
          "No se asombren de esto, porque viene la hora en que todos los que están en las tumbas oirán su voz y saldrán: los que hicieron cosas buenas, para una resurrección de vida, y los que hicieron cosas malas, para una resurrección de juicio. Yo no puedo hacer ni una sola cosa por mi cuenta. Juzgo de acuerdo con lo que oigo, y mi juicio es justo, porque no busco hacer mi voluntad, sino la voluntad del que me envió."
        ]
      },
      {
        "description": "Juan el Bautista, las obras de Jesús, el Padre y las Escrituras dan testimonio de Jesús",
        "timeStart": "00:37:58.23",
        "timeEnd": "00:41:17.14",
        "references": "Juan 5:31-47",
        "refs": [
          {
            "label": "Jn 5:31-47",
            "tv": "43005031-43005047",
            "href": "/es/biblioteca/biblia/biblia-estudio/libros/juan/5/#v43005031-v43005047"
          }
        ],
        "paragraphs": [
          "Si solo yo diera testimonio a mi favor, mi testimonio no sería verdadero.",
          "Pero hay otro que da testimonio a mi favor, y sé que el testimonio que él da acerca de mí es verdadero.",
          "Le enviaron mensajeros a Juan, y él ha dado testimonio de la verdad. Ahora bien, yo no acepto el testimonio de ningún hombre, pero digo estas cosas para que ustedes se salven.",
          "Ese hombre era una lámpara que ardía y brillaba, y ustedes por un poco de tiempo estuvieron dispuestos a alegrarse muchísimo con su luz. Pero mi testimonio tiene más peso que el de Juan, porque las obras que mi Padre me mandó a hacer, estas obras que yo hago, confirman que el Padre me envió. Y el Padre, que me envió, es quien ha dado testimonio acerca de mí.",
          "Ustedes nunca han oído su voz ni han visto su aspecto, y su palabra no reside en ustedes porque no creen al que él envió.",
          "Ustedes estudian con mucho cuidado las Escrituras porque piensan que por medio de ellas tendrán vida eterna; y son estas mismas las que dan testimonio acerca de mí. Aun así, ustedes no quieren acudir a mí para tener vida. Yo no acepto las alabanzas de la gente.",
          "Pero sé muy bien que en ustedes no hay amor a Dios.",
          "Yo he venido en nombre de mi Padre y ustedes no me reciben. Si viniera otro en su propio nombre, a ese sí lo recibirían. ¿Cómo van a creerme ustedes, que aceptan alabanzas unos de otros en vez de buscar la aprobación del único Dios?",
          "No piensen que yo los voy a acusar delante del Padre. El que los acusa a ustedes es Moisés, en quien ponen su esperanza. En realidad, si le creyeran a Moisés, me creerían a mí, porque él escribió sobre mí.",
          "Pero, si no creen en sus escritos, ¿cómo van a creer lo que digo yo?"
        ]
      },
      {
        "description": "Jesús es Señor del sábado",
        "timeStart": "00:42:09.11",
        "timeEnd": "00:44:27.58",
        "references": "Marcos 2:23-28; Mateo 12:1-8; Lucas 6:1-5",
        "refs": [
          {
            "label": "Mr 2:23-28;",
            "tv": "41002023-41002028",
            "href": "/es/biblioteca/biblia/biblia-estudio/libros/marcos/2/#v41002023-v41002028"
          },
          {
            "label": "Mt 12:1-8;",
            "tv": "40012001-40012008",
            "href": "/es/biblioteca/biblia/biblia-estudio/libros/mateo/12/#v40012001-v40012008"
          },
          {
            "label": "Lu 6:1-5",
            "tv": "42006001-42006005",
            "href": "/es/biblioteca/biblia/biblia-estudio/libros/lucas/6/#v42006001-v42006005"
          }
        ],
        "paragraphs": [
          "Ahora bien, él iba cruzando en sábado los campos de cereales, y sus discípulos comenzaron a arrancar algunas espigas mientras caminaban.",
          "¡Mira eso! ¿Por qué están haciendo lo que no está permitido hacer en sábado?",
          "¿Es que nunca han leído lo que hizo David cuando se vio en necesidad y él y sus hombres tuvieron hambre? En el relato acerca del sacerdote principal Abiatar, cuando David entró en la casa de Dios, comió de los panes de la presentación. Y nadie puede comer de ese pan excepto los sacerdotes. Y David también los compartió con sus hombres. Además, ¿no leyeron en la Ley que los sábados los sacerdotes en el templo no respetan el sábado y no por eso son culpables? Pues yo les digo que tienen aquí algo más importante que el templo. Si hubieran entendido qué significan las palabras “Lo que quiero es compasión, no sacrificios”, no habrían condenado a los que no son culpables.",
          "El sábado se hizo para la gente, y no la gente para el sábado.",
          "Así que el Hijo del Hombre es Señor hasta del sábado."
        ]
      },
      {
        "description": "Jesús le cura en sábado la mano paralizada a un hombre",
        "timeStart": "00:44:28.21",
        "timeEnd": "00:48:48.13",
        "references": "Lucas 6:6-11; Mateo 12:9-14; Marcos 3:1-6",
        "refs": [
          {
            "label": "Lu 6:6-11;",
            "tv": "42006006-42006011",
            "href": "/es/biblioteca/biblia/biblia-estudio/libros/lucas/6/#v42006006-v42006011"
          },
          {
            "label": "Mt 12:9-14;",
            "tv": "40012009-40012014",
            "href": "/es/biblioteca/biblia/biblia-estudio/libros/mateo/12/#v40012009-v40012014"
          },
          {
            "label": "Mr 3:1-6",
            "tv": "41003001-41003006",
            "href": "/es/biblioteca/biblia/biblia-estudio/libros/marcos/3/#v41003001-v41003006"
          }
        ],
        "paragraphs": [
          "Otro sábado entró en la sinagoga y se puso a enseñar.",
          "Y había allí un hombre que tenía la mano derecha paralizada.",
          "Los escribas y los fariseos no le quitaban los ojos de encima a Jesús para ver si curaba en sábado. ¿Está permitido curar a alguien en sábado? Y así encontrar un motivo para acusarlo.",
          "Entonces Jesús le pidió al hombre que tenía la mano paralizada: Levántate y ven aquí al centro.",
          "¿Qué está permitido hacer en sábado? ¿Hacer el bien, o hacer daño?",
          "¿Salvar una vida, o quitarla?",
          "Pero ellos se quedaron callados.",
          "Si tienen una oveja y esta se cae en un hoyo en sábado, ¿quién de ustedes no agarraría esa oveja y la sacaría de ahí?",
          "¡Un hombre vale mucho más que una oveja!",
          "De modo que está permitido hacer algo bueno en sábado.",
          "Extiende la mano.",
          "Cuando él la extendió, la mano se le recuperó y quedó sana como la otra.",
          "Entonces los fariseos salieron de allí y de inmediato empezaron a reunirse con los miembros del partido de Herodes para planear la muerte de Jesús."
        ]
      },
      {
        "description": "Una gran multitud en la orilla del mar; Jesús es el siervo amado de Dios; cura a muchos",
        "timeStart": "00:48:50.01",
        "timeEnd": "00:51:02.06",
        "references": "Marcos 3:7-12; Mateo 12:15-21",
        "refs": [
          {
            "label": "Mr 3:7-12;",
            "tv": "41003007-41003012",
            "href": "/es/biblioteca/biblia/biblia-estudio/libros/marcos/3/#v41003007-v41003012"
          },
          {
            "label": "Mt 12:15-21",
            "tv": "40012015-40012021",
            "href": "/es/biblioteca/biblia/biblia-estudio/libros/mateo/12/#v40012015-v40012021"
          }
        ],
        "paragraphs": [
          "Pero Jesús se dirigió al mar con sus discípulos, y una gran multitud de Galilea y de Judea lo siguió.",
          "Hasta de Jerusalén, de Idumea, del otro lado del Jordán y de los alrededores de Tiro y Sidón llegó una gran multitud, pues habían oído todo lo que él hacía.",
          "Así que él les pidió a sus discípulos que le tuvieran lista una pequeña barca para evitar que la multitud lo apretara.",
          "Y es que, como había curado a tantos, todos los que tenían enfermedades graves se le echaban encima para tocarlo. Hasta los espíritus malignos caían a sus pies cuando lo veían, y gritaban: “¡Tú eres el Hijo de Dios!”. Pero una y otra vez Jesús les ordenaba con firmeza que no le dijeran a nadie quién era él.",
          "Así se cumplió lo que se había dicho por medio del profeta Isaías: “Miren, este es mi siervo, a quien elegí; mi amado, quien tiene mi aprobación. Pondré mi espíritu sobre él, y él les aclarará a las naciones lo que es la justicia.",
          "No discutirá ni gritará. Y nadie oirá su voz en las calles principales.",
          "No romperá la caña que está quebrada ni apagará la mecha que apenas arde, hasta que haga triunfar la justicia.",
          "Realmente, las naciones pondrán su esperanza en el nombre de él”."
        ]
      },
      {
        "description": "Jesús elige a los 12 apóstoles",
        "timeStart": "00:51:03.35",
        "timeEnd": "00:54:50.29",
        "references": "Lucas 6:12-16; Marcos 3:13-19a",
        "refs": [
          {
            "label": "Lu 6:12-16;",
            "tv": "42006012-42006016",
            "href": "/es/biblioteca/biblia/biblia-estudio/libros/lucas/6/#v42006012-v42006016"
          },
          {
            "label": "Mr 3:13-19a",
            "tv": "41003013-41003019",
            "href": "/es/biblioteca/biblia/biblia-estudio/libros/marcos/3/#v41003013-v41003019"
          }
        ],
        "paragraphs": [
          "Uno de esos días, él se fue a la montaña a orar y estuvo toda la noche orándole a Dios.",
          "Cuando se hizo de día, llamó a sus discípulos y eligió a 12 de ellos, a los que llamó apóstoles.",
          "En el grupo de 12 que formó estaban Simón (a quien también llamó Pedro), Santiago hijo de Zebedeo y su hermano Juan (a quienes también llamó Boanerges, que significa “hijos del trueno”), Andrés, Felipe, Bartolomé, Mateo, Tomás, Santiago hijo de Alfeo, Tadeo, Simón el Cananita y Judas Iscariote (el que más tarde lo traicionó)."
        ]
      }
    ]
  },
  {
    "episode": 5,
    "fileIndex": 2,
    "day": "Sábado",
    "daySlug": "sabado",
    "title": "Impactados con su manera de enseñar",
    "series": "Episodio 5",
    "guide": "https://www.jw.org/es/biblioteca/%C3%ADndices/guia-videos-buenas-noticias-segun-jesus/Impactados-con-su-manera-de-ense%C3%B1ar-Gu%C3%ADa-de-videos/",
    "scenes": [
      {
        "description": "Jesús enseña y cura a grandes multitudes",
        "timeStart": "00:00:00.00",
        "timeEnd": "00:02:19.76",
        "references": "Lucas 6:17-19; Mateo 5:1",
        "refs": [
          {
            "label": "Lu 6:17-19;",
            "tv": "42006017-42006019",
            "href": "/es/biblioteca/biblia/biblia-estudio/libros/lucas/6/#v42006017-v42006019"
          },
          {
            "label": "Mt 5:1",
            "tv": "40005001",
            "href": "/es/biblioteca/biblia/biblia-estudio/libros/mateo/5/#v40005001"
          }
        ],
        "paragraphs": [
          "Luego bajó con ellos y se detuvo en un lugar llano. Había allí un gran número de sus discípulos ¡Rabí! ¡Rabí! ¡Rabí! y una gran multitud de gente Rabí. de toda Judea, de Jerusalén y de la región costera de Tiro y Sidón.",
          "Habían venido para oírlo y para ser curados de sus enfermedades.",
          "Rabí. Rabí, por favor.",
          "Por favor.",
          "¡Gracias!",
          "Por favor, Rabí. Hasta los que estaban atormentados por espíritus malignos quedaban curados.",
          "Y toda la multitud intentaba tocarlo porque de él salía un poder que los curaba a todos."
        ]
      },
      {
        "description": "Jesús comienza el Sermón del Monte; felicidades y ayes",
        "timeStart": "00:02:31.03",
        "timeEnd": "00:05:15.19",
        "references": "Mateo 5:2-12; Lucas 6:20-26",
        "refs": [
          {
            "label": "Mt 5:2-12;",
            "tv": "40005002-40005012",
            "href": "/es/biblioteca/biblia/biblia-estudio/libros/mateo/5/#v40005002-v40005012"
          },
          {
            "label": "Lu 6:20-26",
            "tv": "42006020-42006026",
            "href": "/es/biblioteca/biblia/biblia-estudio/libros/lucas/6/#v42006020-v42006026"
          }
        ],
        "paragraphs": [
          "Felices los que reconocen sus necesidades espirituales, porque el Reino de los cielos es de ellos. Felices los que se lamentan, porque serán consolados. Felices los que son apacibles, porque van a heredar la tierra.",
          "Felices los que tienen hambre y sed de justicia, porque serán saciados.",
          "Felices los que son misericordiosos, porque serán tratados con misericordia. Felices los que tienen un corazón puro, porque verán a Dios.",
          "Felices los que fomentan la paz, porque serán llamados hijos de Dios.",
          "Felices los que han sido perseguidos por causa de la justicia, porque el Reino de los cielos es de ellos.",
          "Felices ustedes cuando, por causa de mí, la gente los insulte, los persiga y, mintiendo, diga todo tipo de cosas malas sobre ustedes. Estén felices y radiantes de alegría, ya que su recompensa es grande en los cielos, porque a los profetas que vivieron antes que ustedes también los persiguieron así.",
          "Pero ¡ay de ustedes, los ricos, porque ya han recibido todo su consuelo! ¡Ay de ustedes, los que ahora están saciados, porque pasarán hambre! ¡Ay de ustedes, los que ahora ríen, porque se lamentarán y llorarán! ¡Ay cuando todos hablen bien de ustedes, porque eso es lo que los antepasados de ellos hicieron con los profetas falsos!"
        ]
      },
      {
        "description": "“La sal de la tierra” y “la luz del mundo”",
        "timeStart": "00:05:15.98",
        "timeEnd": "00:06:12.91",
        "references": "Mateo 5:13-16",
        "refs": [
          {
            "label": "Mt 5:13-16",
            "tv": "40005013-40005016",
            "href": "/es/biblioteca/biblia/biblia-estudio/libros/mateo/5/#v40005013-v40005016"
          }
        ],
        "paragraphs": [
          "Ustedes son la sal de la tierra.",
          "Pero, si la sal pierde su fuerza, ¿acaso puede volver a ser salada? Ya no sirve para nada, sino para echarla afuera y que la gente la pisotee.",
          "Ustedes son la luz del mundo. No se puede esconder una ciudad que está en lo alto de una montaña. Nadie enciende una lámpara para luego taparla con una canasta, la pone en el candelero para que alumbre a todos los que están en la casa. De la misma manera, hagan brillar su luz a la vista de la gente. Que vean sus buenas obras y así le den gloria a su Padre que está en los cielos."
        ]
      },
      {
        "description": "Jesús vino a cumplir la Ley",
        "timeStart": "00:06:12.96",
        "timeEnd": "00:07:37.08",
        "references": "Mateo 5:17-20",
        "refs": [
          {
            "label": "Mt 5:17-20",
            "tv": "40005017-40005020",
            "href": "/es/biblioteca/biblia/biblia-estudio/libros/mateo/5/#v40005017-v40005020"
          }
        ],
        "paragraphs": [
          "No piensen que vine a anular la Ley o los Profetas. No vine a anular, sino a cumplir.",
          "Yo les aseguro que no desaparecerá ni la más pequeña letra ni un trazo de una letra de la Ley hasta que todo suceda. ¡Antes desaparecerían el cielo y la tierra! Por eso, quien desobedezca uno de sus mandamientos más pequeños y les enseñe a otros a hacer lo mismo será considerado más pequeño con relación al Reino de los cielos. En cambio, quien los obedezca y se los enseñe a otros será considerado grande con relación al Reino de los cielos.",
          "Les digo que, si ustedes no son más justos que los escribas y los fariseos, nunca van a entrar en el Reino de los cielos."
        ]
      },
      {
        "description": "Enseñanzas sobre la ira y los desacuerdos",
        "timeStart": "00:07:37.92",
        "timeEnd": "00:09:22.98",
        "references": "Mateo 5:21-26",
        "refs": [
          {
            "label": "Mt 5:21-26",
            "tv": "40005021-40005026",
            "href": "/es/biblioteca/biblia/biblia-estudio/libros/mateo/5/#v40005021-v40005026"
          }
        ],
        "paragraphs": [
          "Ya oyeron que a sus antepasados se les dijo: “No asesines, y todo el que cometa un asesinato tendrá que responder ante el tribunal de justicia”. Pero yo les digo que tendrá que responder ante el tribunal de justicia todo el que siga furioso con su hermano. Y todo el que insulte con desprecio a su hermano tendrá que responder ante el Tribunal Supremo.",
          "Pero todo el que le diga “¡Eres un estúpido despreciable!” se arriesga a acabar en la Gehena de fuego.",
          "Por eso, si estás llevando tu ofrenda al altar y allí te acuerdas de que tu hermano tiene algo contra ti, deja tu ofrenda allí, delante del altar, y vete. Primero haz las paces con tu hermano, y luego vuelve y presenta tu ofrenda. Si un adversario te lleva a juicio, trata de resolver las cosas cuanto antes, mientras aún van de camino al tribunal, no sea que tu adversario te entregue al juez, luego el juez te entregue al guardia del tribunal y tú acabes en prisión.",
          "Yo te aseguro que de ningún modo saldrás de allí hasta que hayas pagado la última monedita."
        ]
      },
      {
        "description": "Enseñanzas sobre el adulterio y el divorcio",
        "timeStart": "00:09:23.06",
        "timeEnd": "00:10:57.20",
        "references": "Mateo 5:27-32",
        "refs": [
          {
            "label": "Mt 5:27-32",
            "tv": "40005027-40005032",
            "href": "/es/biblioteca/biblia/biblia-estudio/libros/mateo/5/#v40005027-v40005032"
          }
        ],
        "paragraphs": [
          "Ustedes oyeron que se dijo: “No cometas adulterio”. Pero yo les digo que todo el que sigue mirando a una mujer hasta el punto de sentir pasión por ella ya ha cometido adulterio con ella en su corazón.",
          "Por eso, si tu ojo derecho te está haciendo tropezar, arráncatelo y échalo lejos. Es preferible que pierdas uno de tus miembros a que todo tu cuerpo sea arrojado a la Gehena.",
          "Igualmente, si tu mano derecha te está haciendo tropezar, córtatela y échala lejos. Es preferible que pierdas uno de tus miembros a que todo tu cuerpo vaya a parar a la Gehena.",
          "También se dijo: “Que todo el que se divorcie de su esposa le dé un certificado de divorcio”. Pero yo les digo que todo el que se divorcia de su esposa",
          "—a menos que sea por inmoralidad sexual— la pone en peligro de cometer adulterio, y cualquiera que se case con la divorciada también comete adulterio."
        ]
      },
      {
        "description": "Enseñanzas sobre los juramentos, la venganza y el amor a los enemigos",
        "timeStart": "00:10:57.74",
        "timeEnd": "00:14:54.35",
        "references": "Mateo 5:33-48; Lucas 6:27-30, 32-36",
        "refs": [
          {
            "label": "Mt 5:33-48;",
            "tv": "40005033-40005048",
            "href": "/es/biblioteca/biblia/biblia-estudio/libros/mateo/5/#v40005033-v40005048"
          },
          {
            "label": "Lu 6:27-30,",
            "tv": "42006027-42006030",
            "href": "/es/biblioteca/biblia/biblia-estudio/libros/lucas/6/#v42006027-v42006030"
          },
          {
            "label": "32-36",
            "tv": "42006032-42006036",
            "href": "/es/biblioteca/biblia/biblia-estudio/libros/lucas/6/#v42006032-v42006036"
          }
        ],
        "paragraphs": [
          "También oyeron que a sus antepasados se les dijo: “No jures para luego no cumplir; cumple los votos que le hagas a Jehová”. Pero yo les digo: no juren nunca; ni por el cielo, porque es el trono de Dios; ni por la tierra, porque es el banquillo para sus pies; ni por Jerusalén, porque es la ciudad del gran Rey. Tampoco jures por tu cabeza, porque no puedes volver blanco o negro ni un solo cabello.",
          "Simplemente, cuando digan “sí”, que sea sí, y, cuando digan “no”, que sea no. Cualquier otra cosa que se diga viene del Maligno.",
          "Ustedes oyeron que se dijo: “Ojo por ojo y diente por diente”. Pero yo les digo: no le hagan frente a alguien malo. Al que te dé una bofetada en la mejilla derecha, ofrécele también la otra mejilla. Y, si alguien quiere llevarte al tribunal para quedarse con tu túnica, deja que se quede también con tu manto. Y, si alguien con autoridad te obliga a prestarle un servicio por una milla, ve con él dos millas. Al que te pide algo, dáselo. Y, al que te pide que le prestes, no le des la espalda.",
          "Ustedes oyeron que se dijo: “Ama a tu prójimo y odia a tu enemigo”.",
          "Pero yo les digo que amen a sus enemigos y oren por los que los persiguen. Así demostrarán que son hijos de su Padre que está en los cielos, ya que él hace salir su sol sobre malos y buenos, y envía la lluvia sobre justos e injustos.",
          "Porque, si aman a los que los aman, ¿qué recompensa merecen? ¿Acaso no hacen lo mismo los cobradores de impuestos?",
          "Si tratan bien a los que los tratan bien, ¿qué mérito tienen? Hasta los pecadores hacen eso.",
          "Y, si solo saludan a sus hermanos, ¿qué tiene eso de especial?",
          "¿Acaso no hace lo mismo la gente de las naciones?",
          "Y, si les prestan algo a quienes ustedes piensan que van a devolvérselo, ¿qué mérito tienen? Hasta los pecadores les prestan a otros para recibir lo mismo de vuelta. Ustedes, en cambio, amen a sus enemigos, hagan el bien y presten sin esperar que se les devuelva nada. Entonces, su recompensa será grande y serán hijos del Altísimo, porque él es bondadoso hasta con los desagradecidos y malvados. Por lo tanto, sean perfectos, tal como su Padre celestial es perfecto."
        ]
      },
      {
        "description": "Cuidado con hacer lo correcto para lucirse",
        "timeStart": "00:14:54.39",
        "timeEnd": "00:15:58.83",
        "references": "Mateo 6:1-4",
        "refs": [
          {
            "label": "Mt 6:1-4",
            "tv": "40006001-40006004",
            "href": "/es/biblioteca/biblia/biblia-estudio/libros/mateo/6/#v40006001-v40006004"
          }
        ],
        "paragraphs": [
          "Cuidado con hacer lo que es correcto delante de la gente para que ellos los vean. Si hacen eso, no recibirán ninguna recompensa de su Padre. Cuando le des ayuda a un necesitado, no vayas tocando la trompeta como hacen los hipócritas en las sinagogas y en las calles para que los demás los alaben.",
          "Les aseguro que ellos ya han recibido toda su recompensa. Más bien, cuando le des ayuda a un necesitado, que tu mano izquierda no sepa lo que hace tu mano derecha; así la ayuda que les des a los necesitados se mantendrá en secreto. Y entonces tu Padre, que mira en secreto, te lo pagará."
        ]
      },
      {
        "description": "Cómo orar; la oración modelo",
        "timeStart": "00:15:58.87",
        "timeEnd": "00:18:19.68",
        "references": "Mateo 6:5-15",
        "refs": [
          {
            "label": "Mt 6:5-15",
            "tv": "40006005-40006015",
            "href": "/es/biblioteca/biblia/biblia-estudio/libros/mateo/6/#v40006005-v40006015"
          }
        ],
        "paragraphs": [
          "También, cuando oren, no hagan como los hipócritas. A ellos les gusta orar de pie en las sinagogas y en las esquinas de las calles principales para que los demás los vean. Les aseguro que ellos ya han recibido toda su recompensa. En cambio tú, cuando vayas a orar, entra en tu cuarto y, después de cerrar la puerta, órale a tu Padre, que está en lo secreto. Y entonces tu Padre, que mira en secreto, te lo pagará.",
          "Cuando ores, no repitas lo mismo una y otra vez, como hace la gente de las naciones, que cree que será escuchada por usar muchas palabras. No sean como ellos. Su Padre ya sabe lo que ustedes necesitan incluso antes de que se lo pidan.",
          "Ustedes deben orar de esta manera: “Padre nuestro que estás en los cielos, que tu nombre sea santificado. Que venga tu Reino. Que se haga tu voluntad, como en el cielo, también en la tierra.",
          "Danos hoy nuestro pan para este día; perdónanos nuestras deudas, como nosotros también perdonamos a nuestros deudores. Y no nos dejes caer en la tentación, sino líbranos del Maligno”.",
          "Porque, si ustedes les perdonan a otros sus ofensas, su Padre celestial también los perdonará a ustedes.",
          "Pero, si no les perdonan sus ofensas a los demás, su Padre tampoco perdonará las ofensas de ustedes."
        ]
      },
      {
        "description": "No ayunar con hipocresía",
        "timeStart": "00:18:19.72",
        "timeEnd": "00:19:15.49",
        "references": "Mateo 6:16-18",
        "refs": [
          {
            "label": "Mt 6:16-18",
            "tv": "40006016-40006018",
            "href": "/es/biblioteca/biblia/biblia-estudio/libros/mateo/6/#v40006016-v40006018"
          }
        ],
        "paragraphs": [
          "Cuando ayunen, dejen de poner cara triste, como hacen los hipócritas, porque ellos cambian el aspecto de su rostro para que los demás vean que están ayunando.",
          "Les aseguro que ellos ya han recibido toda su recompensa. Pero tú, cuando ayunes, ponte aceite perfumado en la cabeza y lávate la cara para que no sea la gente la que te vea ayunando, sino solo tu Padre, que está en lo secreto. Y entonces tu Padre, que mira en secreto, te lo pagará."
        ]
      },
      {
        "description": "Tesoros en la tierra y en el cielo",
        "timeStart": "00:19:15.53",
        "timeEnd": "00:20:41.11",
        "references": "Mateo 6:19-24",
        "refs": [
          {
            "label": "Mt 6:19-24",
            "tv": "40006019-40006024",
            "href": "/es/biblioteca/biblia/biblia-estudio/libros/mateo/6/#v40006019-v40006024"
          }
        ],
        "paragraphs": [
          "Dejen de acumular tesoros en la tierra, donde las polillas y el óxido los echan a perder y donde los ladrones entran a robar.",
          "Más bien, acumulen para ustedes tesoros en el cielo, donde ni las polillas ni el óxido los echan a perder y donde los ladrones no entran a robar. Porque, donde esté tu tesoro, ahí también estará tu corazón.",
          "La lámpara del cuerpo son los ojos. Si tus ojos están bien enfocados, todo tu cuerpo brillará. Pero, si tus ojos son envidiosos, todo tu cuerpo estará oscuro. Si la luz que hay en ti en realidad es oscuridad, ¡qué oscuridad tan grande la tuya!",
          "Nadie puede ser esclavo de dos amos, porque odiará a uno y amará al otro, o le será leal a uno y despreciará al otro. No pueden ser esclavos de Dios y a la vez de las Riquezas."
        ]
      },
      {
        "description": "“Dejen de angustiarse”; “sigan buscando primero el Reino”",
        "timeStart": "00:20:41.16",
        "timeEnd": "00:23:28.87",
        "references": "Mateo 6:25-34",
        "refs": [
          {
            "label": "Mt 6:25-34",
            "tv": "40006025-40006034",
            "href": "/es/biblioteca/biblia/biblia-estudio/libros/mateo/6/#v40006025-v40006034"
          }
        ],
        "paragraphs": [
          "Por eso les digo: dejen de angustiarse por su vida, por lo que van a comer y beber; o por su cuerpo, por lo que van a ponerse.",
          "¿No vale más la vida que el alimento y el cuerpo que la ropa?",
          "Observen con atención las aves del cielo. No siembran ni cosechan ni almacenan en graneros, pero su Padre celestial las alimenta. ¿Y acaso no valen ustedes más que ellas?",
          "¿Quién de ustedes, por angustiarse, puede alargar un solo codo la duración de su vida?",
          "Además, ¿por qué se angustian por la ropa? Aprendan una lección de cómo crecen los lirios del campo.",
          "No trabajan duro ni hilan; pero les digo que ni siquiera Salomón en toda su gloria se vistió como uno de ellos. Entonces, si Dios viste así a la vegetación del campo, que hoy está aquí y mañana se echa al horno, ¿no los vestirá a ustedes con mucha más razón, gente de poca fe?",
          "Así que nunca se angustien y digan: “¿Qué vamos a comer?”, o “¿Qué vamos a beber?”, o “¿Qué vamos a ponernos?”. Porque es la gente de las naciones la que busca estas cosas con tanto empeño. Su Padre celestial sabe que ustedes necesitan todas estas cosas.",
          "Por lo tanto, sigan buscando primero el Reino y la justicia de Dios, y entonces recibirán también todas esas cosas.",
          "Así que nunca se angustien por el día siguiente, porque el día siguiente traerá sus propias preocupaciones. Bastante hay con los problemas de cada día."
        ]
      },
      {
        "description": "“Dejen de juzgar”; “tengan la costumbre de dar”",
        "timeStart": "00:23:28.91",
        "timeEnd": "00:25:09.09",
        "references": "Mateo 7:1-6; Lucas 6:37-42",
        "refs": [
          {
            "label": "Mt 7:1-6;",
            "tv": "40007001-40007006",
            "href": "/es/biblioteca/biblia/biblia-estudio/libros/mateo/7/#v40007001-v40007006"
          },
          {
            "label": "Lu 6:37-42",
            "tv": "42006037-42006042",
            "href": "/es/biblioteca/biblia/biblia-estudio/libros/lucas/6/#v42006037-v42006042"
          }
        ],
        "paragraphs": [
          "Dejen de juzgar, para que no sean juzgados. Porque así como juzguen a otros serán juzgados ustedes, y la medida que usen con otros es la que usarán con ustedes.",
          "¿Por qué miras la paja que tiene tu hermano en su ojo pero no te fijas en la viga que tienes en el tuyo? ¿Y cómo puedes decirle a tu hermano “déjame sacarte la paja del ojo”, si resulta que tú tienes una viga en el tuyo? ¡Hipócrita! Primero sácate la viga de tu ojo y verás claramente cómo sacar la paja del ojo de tu hermano.",
          "Tengan la costumbre de dar y también se les dará. Les echarán en el pliegue de su ropa una medida generosa, apretada, sacudida y rebosante. Porque la medida que usen con otros es la que usarán con ustedes.",
          "No les den cosas santas a los perros. Tampoco echen sus perlas delante de los cerdos, no sea que las pisoteen, se vuelvan contra ustedes y los hagan pedazos."
        ]
      },
      {
        "description": "Seguir pidiendo, buscando y tocando a la puerta",
        "timeStart": "00:25:09.13",
        "timeEnd": "00:26:08.48",
        "references": "Mateo 7:7-11",
        "refs": [
          {
            "label": "Mt 7:7-11",
            "tv": "40007007-40007011",
            "href": "/es/biblioteca/biblia/biblia-estudio/libros/mateo/7/#v40007007-v40007011"
          }
        ],
        "paragraphs": [
          "Sigan pidiendo y se les dará, sigan buscando y encontrarán, sigan tocando a la puerta y se les abrirá. Porque todo el que pide recibe, y todo el que busca encuentra, y a todo el que toca a la puerta se le abrirá. Si su hijo les pide pan, ¿quién de ustedes le da una piedra?",
          "Y, si les pide un pescado, ¿verdad que no le dan una serpiente?",
          "Por lo tanto, si ustedes, aunque son malos, saben darles buenos regalos a sus hijos, ¡con mucha más razón su Padre que está en los cielos les dará cosas buenas a quienes se las piden!"
        ]
      },
      {
        "description": "La Regla de Oro",
        "timeStart": "00:26:08.53",
        "timeEnd": "00:26:31.30",
        "references": "Mateo 7:12; Lucas 6:31",
        "refs": [
          {
            "label": "Mt 7:12;",
            "tv": "40007012",
            "href": "/es/biblioteca/biblia/biblia-estudio/libros/mateo/7/#v40007012"
          },
          {
            "label": "Lu 6:31",
            "tv": "42006031",
            "href": "/es/biblioteca/biblia/biblia-estudio/libros/lucas/6/#v42006031"
          }
        ],
        "paragraphs": [
          "Por eso, todo lo que les gustaría que hicieran por ustedes háganlo también por los demás.",
          "De hecho, en eso se resumen la Ley y los Profetas."
        ]
      },
      {
        "description": "La puerta angosta",
        "timeStart": "00:26:33.43",
        "timeEnd": "00:26:55.95",
        "references": "Mateo 7:13, 14",
        "refs": [
          {
            "label": "Mt 7:13, 14",
            "tv": "40007013-40007014",
            "href": "/es/biblioteca/biblia/biblia-estudio/libros/mateo/7/#v40007013-v40007014"
          }
        ],
        "paragraphs": [
          "Entren por la puerta angosta. Porque ancha es la puerta y espacioso es el camino que lleva a la destrucción, y son muchos los que entran por esa puerta; mientras que angosta es la puerta y estrecho es el camino que lleva a la vida, y pocos lo encuentran."
        ]
      },
      {
        "description": "Los profetas falsos; los árboles se reconocen por sus frutos",
        "timeStart": "00:26:55.99",
        "timeEnd": "00:28:40.09",
        "references": "Mateo 7:15-23; Lucas 6:43-46",
        "refs": [
          {
            "label": "Mt 7:15-23;",
            "tv": "40007015-40007023",
            "href": "/es/biblioteca/biblia/biblia-estudio/libros/mateo/7/#v40007015-v40007023"
          },
          {
            "label": "Lu 6:43-46",
            "tv": "42006043-42006046",
            "href": "/es/biblioteca/biblia/biblia-estudio/libros/lucas/6/#v42006043-v42006046"
          }
        ],
        "paragraphs": [
          "Cuidado con los profetas falsos, que se les acercan disfrazados de oveja pero por dentro son lobos voraces. Los reconocerán por sus frutos.",
          "Nunca se recogen uvas de los espinos ni higos de los cardos, ¿verdad? Igualmente, un árbol bueno da frutos buenos, pero un árbol podrido da frutos malos. Un árbol bueno no puede dar frutos malos y un árbol podrido no puede dar frutos buenos. Todo árbol que no da frutos buenos se corta y se echa al fuego.",
          "Así que a esos hombres los reconocerán por sus frutos.",
          "No todos los que me dicen “Señor, Señor” entrarán en el Reino de los cielos. Solo entrarán los que hacen la voluntad de mi Padre que está en los cielos. Ese día, muchos me dirán: “Señor, Señor, ¿acaso no profetizamos en tu nombre y en tu nombre expulsamos demonios y en tu nombre hicimos muchos milagros?”.",
          "Pero entonces les diré: “¡Yo a ustedes nunca los conocí! ¡Aléjense de mí, ustedes que violan la ley!”."
        ]
      },
      {
        "description": "La casa construida sobre la roca y la casa construida sobre la arena",
        "timeStart": "00:28:40.14",
        "timeEnd": "00:29:55.63",
        "references": "Mateo 7:24-27; Lucas 6:47-49",
        "refs": [
          {
            "label": "Mt 7:24-27;",
            "tv": "40007024-40007027",
            "href": "/es/biblioteca/biblia/biblia-estudio/libros/mateo/7/#v40007024-v40007027"
          },
          {
            "label": "Lu 6:47-49",
            "tv": "42006047-42006049",
            "href": "/es/biblioteca/biblia/biblia-estudio/libros/lucas/6/#v42006047-v42006049"
          }
        ],
        "paragraphs": [
          "Por lo tanto, todo el que escuche lo que he dicho y lo haga será como el hombre prudente que construyó su casa sobre la roca.",
          "Cayó la lluvia, crecieron las aguas, los vientos soplaron con fuerza y golpearon contra aquella casa..., pero la casa no se vino abajo, porque tenía los cimientos en la roca.",
          "En cambio, todo el que escuche lo que he dicho pero no lo haga será como el hombre insensato que construyó su casa sobre la arena. Cayó la lluvia, crecieron las aguas, los vientos soplaron con fuerza y sacudieron la casa..., y la casa se vino abajo. Su caída fue tremenda."
        ]
      },
      {
        "description": "Multitudes impactadas al escuchar a Jesús",
        "timeStart": "00:29:55.67",
        "timeEnd": "00:30:42.67",
        "references": "Mateo 7:28, 29",
        "refs": [
          {
            "label": "Mt 7:28, 29",
            "tv": "40007028-40007029",
            "href": "/es/biblioteca/biblia/biblia-estudio/libros/mateo/7/#v40007028-v40007029"
          }
        ],
        "paragraphs": [
          "Cuando Jesús terminó de decir estas cosas, las multitudes estaban impactadas con su manera de enseñar porque les enseñaba como una persona con autoridad, y no como sus escribas."
        ]
      }
    ]
  },
  {
    "episode": 6,
    "fileIndex": 3,
    "day": "Domingo",
    "daySlug": "domingo",
    "title": "¿Eres tú el que tiene que venir?",
    "series": "Episodio 6",
    "guide": "https://www.jw.org/es/biblioteca/%C3%ADndices/guia-videos-buenas-noticias-segun-jesus/Eres-t%C3%BA-el-que-tiene-que-venir-Gu%C3%ADa-de-videos/",
    "scenes": [
      {
        "description": "La fe de un oficial del ejército",
        "timeStart": "00:00:00.00",
        "timeEnd": "00:04:31.90",
        "references": "Lucas 7:1-10; Mateo 8:5-13",
        "refs": [
          {
            "label": "Lu 7:1-10;",
            "tv": "42007001-42007010",
            "href": "/es/biblioteca/biblia/biblia-estudio/libros/lucas/7/#v42007001-v42007010"
          },
          {
            "label": "Mt 8:5-13",
            "tv": "40008005-40008013",
            "href": "/es/biblioteca/biblia/biblia-estudio/libros/mateo/8/#v40008005-v40008013"
          }
        ],
        "paragraphs": [
          "Después de haberle dicho al pueblo lo que tenía que decirle, entró en Capernaúm.",
          "Ahora bien, había un oficial del ejército que tenía un esclavo al que apreciaba mucho y que estaba muy enfermo, a punto de morir.",
          "Cuando oyó hablar de Jesús, mandó a algunos ancianos de los judíos a pedirle que viniera a curar a su esclavo.",
          "Ellos fueron adonde estaba Jesús y se pusieron a suplicarle con insistencia. Este hombre se merece que le hagas ese favor, porque ama a nuestra nación y él fue quien nos construyó la sinagoga.",
          "Así que Jesús se fue con ellos.",
          "Pero, cuando ya estaba cerca de la casa, el oficial del ejército envió a unos amigos a decirle: Señor, no te molestes en venir, porque no merezco que entres bajo mi techo. Tampoco me consideré digno de presentarme ante ti. Pero da la orden y mi siervo se curará. Porque yo también obedezco órdenes y doy órdenes a los soldados que están bajo mi mando. A uno le digo ‘¡Vete!’ y se va, y a otro le digo ‘¡Ven!’ y viene, y a mi esclavo le digo ‘¡Haz esto!’ y lo hace.",
          "Al oír eso, Jesús se quedó asombrado y les dijo a los que lo seguían: Les aseguro que no he encontrado a nadie en Israel que tenga una fe tan grande.",
          "Les digo que muchos vendrán del este y del oeste y se sentarán a la mesa con Abrahán, Isaac y Jacob en el Reino de los cielos, mientras que los hijos del Reino serán echados afuera, a la oscuridad. Ahí es donde llorarán y apretarán los dientes.",
          "Ve y dile: “Que lo que pediste se cumpla de acuerdo con la fe que demostraste”.",
          "¡Señor!",
          "Y en ese momento su siervo se curó.",
          "Cuando los enviados regresaron a la casa, encontraron al esclavo bien de salud."
        ]
      },
      {
        "description": "Jesús resucita al hijo de una viuda en Naín",
        "timeStart": "00:04:57.30",
        "timeEnd": "00:08:56.83",
        "references": "Lucas 7:11-17",
        "refs": [
          {
            "label": "Lu 7:11-17",
            "tv": "42007011-42007017",
            "href": "/es/biblioteca/biblia/biblia-estudio/libros/lucas/7/#v42007011-v42007017"
          }
        ],
        "paragraphs": [
          "Poco después de esto, viajó a una ciudad llamada Naín, y sus discípulos y una gran multitud viajaban con él.",
          "Al acercarse a la puerta de la ciudad, resulta que estaban sacando a un muerto, el único hijo de una mujer. Además, ella era viuda.",
          "También iba con ella una multitud bastante grande de la ciudad.",
          "Cuando el Señor vio a la mujer, se conmovió profundamente.",
          "No llores más.",
          "Enseguida se acercó y tocó la camilla funeraria, y los que la llevaban se detuvieron.",
          "Joven, a ti te digo: ¡levántate!",
          "El muerto se sentó y empezó a hablar. ¿Qué pasó?",
          "¡Mi hijo! ¡Mi hijo, mi hijo! ¡Mi hijo! ¡Estás vivo, hijo!",
          "Y Jesús se lo entregó a su madre.",
          "Todos se quedaron muy impresionados y empezaron a glorificar a Dios diciendo: “Un gran profeta ha surgido entre nosotros”, y “Dios se ha acordado de su pueblo”.",
          "Y estas noticias acerca de él se extendieron por toda Judea y por toda aquella región."
        ]
      },
      {
        "description": "Juan el Bautista pregunta si Jesús es “el que tiene que venir”",
        "timeStart": "00:08:58.79",
        "timeEnd": "00:12:27.96",
        "references": "Lucas 7:18-23; Mateo 11:2-6",
        "refs": [
          {
            "label": "Lu 7:18-23;",
            "tv": "42007018-42007023",
            "href": "/es/biblioteca/biblia/biblia-estudio/libros/lucas/7/#v42007018-v42007023"
          },
          {
            "label": "Mt 11:2-6",
            "tv": "40011002-40011006",
            "href": "/es/biblioteca/biblia/biblia-estudio/libros/mateo/11/#v40011002-v40011006"
          }
        ],
        "paragraphs": [
          "Entonces los discípulos de Juan le contaron a este todas estas cosas.",
          "De modo que Juan mandó llamar a dos de sus discípulos y los envió a preguntarle al Señor: ¿Eres tú el que tiene que venir, o tenemos que esperar a otro?",
          "Cuando llegaron adonde estaba Jesús, los hombres le dijeron: Juan el Bautista nos envió a preguntarte si eres tú el que tiene que venir o si tenemos que esperar a otro.",
          "En ese momento, él curó a muchas personas de enfermedades, de dolencias graves y de espíritus malvados, y les concedió la vista a muchos ciegos.",
          "Vayan y cuéntenle a Juan lo que han visto y oído: ahora los ciegos ven, los lisiados caminan, los leprosos quedan limpios, los sordos oyen, los muertos son resucitados y a los pobres se les anuncian las buenas noticias.",
          "Feliz el que no tropieza por mi causa."
        ]
      },
      {
        "description": "Jesús elogia a Juan el Bautista",
        "timeStart": "00:12:29.58",
        "timeEnd": "00:14:53.77",
        "references": "Lucas 7:24-30; Mateo 11:7-15",
        "refs": [
          {
            "label": "Lu 7:24-30;",
            "tv": "42007024-42007030",
            "href": "/es/biblioteca/biblia/biblia-estudio/libros/lucas/7/#v42007024-v42007030"
          },
          {
            "label": "Mt 11:7-15",
            "tv": "40011007-40011015",
            "href": "/es/biblioteca/biblia/biblia-estudio/libros/mateo/11/#v40011007-v40011015"
          }
        ],
        "paragraphs": [
          "Cuando los mensajeros de Juan se habían ido, Jesús se puso a hablarles a las multitudes acerca de Juan.",
          "¿Qué salieron a ver en el desierto? ¿Una caña sacudida por el viento? Entonces, ¿qué salieron a ver? ¿A un hombre vestido con ropa fina? ¡Si los que llevan ropa espléndida y viven rodeados de lujo están en casas de reyes! Pero, entonces, ¿qué salieron a ver? ¿A un profeta? Les digo que sí, y mucho más que un profeta. Es aquel de quien está escrito: “¡Mira! Voy a enviar a mi mensajero delante de ti, y él irá delante de ti preparándote el camino”. ¡Miren, el Cordero de Dios!",
          "Les digo que entre los seres humanos no hay nadie mayor que Juan.",
          "Sin embargo, el que es menor en el Reino de Dios es mayor que él.",
          "Desde los días de Juan el Bautista, el Reino de los cielos es la meta hacia la que la gente avanza con empeño. Y los que avanzan con empeño logran alcanzarlo. Porque, hasta la llegada de Juan, tanto los Profetas como la Ley profetizaron lo que pasaría. Quieran aceptarlo o no, él es el “Elías que tenía que venir”.",
          "El que tenga oídos, que escuche con atención. Cuando todo el pueblo y los cobradores de impuestos oyeron esto, declararon que Dios es justo, pues habían sido bautizados con el bautismo de Juan.",
          "Pero los fariseos y los expertos en la Ley, al no haber aceptado que él los bautizara, despreciaron la dirección que Dios les había dado."
        ]
      },
      {
        "description": "Una generación indiferente",
        "timeStart": "00:14:54.44",
        "timeEnd": "00:15:51.95",
        "references": "Mateo 11:16-19; Lucas 7:31-35",
        "refs": [
          {
            "label": "Mt 11:16-19;",
            "tv": "40011016-40011019",
            "href": "/es/biblioteca/biblia/biblia-estudio/libros/mateo/11/#v40011016-v40011019"
          },
          {
            "label": "Lu 7:31-35",
            "tv": "42007031-42007035",
            "href": "/es/biblioteca/biblia/biblia-estudio/libros/lucas/7/#v42007031-v42007035"
          }
        ],
        "paragraphs": [
          "¿Con quién compararé a esta generación? Es como los niños que están sentados en las plazas de mercado y les gritan a sus compañeros de juegos: “Les tocamos la flauta, pero ustedes no bailaron; les cantamos canciones de duelo, pero ustedes no se golpearon el pecho de tristeza”.",
          "Porque llegó Juan sin comer ni beber y la gente dice: “Tiene un demonio”.",
          "Y llegó el Hijo del Hombre, que sí come y bebe, y la gente dice: “¡Miren! Un glotón y un bebedor de vino, que es amigo de cobradores de impuestos y pecadores”.",
          "En cualquier caso, la sabiduría queda demostrada por sus resultados."
        ]
      },
      {
        "description": "Jesús condena a Corazín, Betsaida y Capernaúm",
        "timeStart": "00:15:53.49",
        "timeEnd": "00:16:52.01",
        "references": "Mateo 11:20-24",
        "refs": [
          {
            "label": "Mt 11:20-24",
            "tv": "40011020-40011024",
            "href": "/es/biblioteca/biblia/biblia-estudio/libros/mateo/11/#v40011020-v40011024"
          }
        ],
        "paragraphs": [
          "Entonces, empezó a reprender a las ciudades donde había hecho la mayoría de sus milagros, porque no se habían arrepentido: ¡Ay de ti, Corazín! ¡Ay de ti, Betsaida! Porque, si los milagros que se hicieron en ustedes se hubieran hecho en Tiro y en Sidón, hace tiempo que se habrían arrepentido con tela de saco y ceniza. Les digo que el Día del Juicio les será más soportable a Tiro y a Sidón que a ustedes. Y tú, Capernaúm, ¿acaso vas a ser elevada hasta el cielo? Bajarás hasta la Tumba. Porque, si los milagros que se hicieron en ti se hubieran hecho en Sodoma, esa ciudad todavía existiría. Te digo que el Día del Juicio le será más soportable a la tierra de Sodoma que a ti."
        ]
      },
      {
        "description": "Jesús alaba a su Padre por favorecer a los humildes",
        "timeStart": "00:17:00.31",
        "timeEnd": "00:18:11.34",
        "references": "Mateo 11:25-27",
        "refs": [
          {
            "label": "Mt 11:25-27",
            "tv": "40011025-40011027",
            "href": "/es/biblioteca/biblia/biblia-estudio/libros/mateo/11/#v40011025-v40011027"
          }
        ],
        "paragraphs": [
          "Te alabo públicamente, Padre, Señor del cielo y la tierra, porque has escondido estas cosas de los intelectuales y sabios, y se las has revelado a los niños pequeños.",
          "Sí, Padre mío, porque te ha parecido bien hacerlo así.",
          "Mi Padre me ha entregado todas las cosas. Nadie conoce realmente al Hijo excepto el Padre. Y nadie conoce realmente al Padre excepto el Hijo y todo aquel a quien el Hijo se lo quiera revelar."
        ]
      },
      {
        "description": "El yugo de Jesús es un alivio para sus discípulos",
        "timeStart": "00:18:11.76",
        "timeEnd": "00:18:53.76",
        "references": "Mateo 11:28-30",
        "refs": [
          {
            "label": "Mt 11:28-30",
            "tv": "40011028-40011030",
            "href": "/es/biblioteca/biblia/biblia-estudio/libros/mateo/11/#v40011028-v40011030"
          }
        ],
        "paragraphs": [
          "Vengan a mí, todos ustedes, que trabajan duro y están sobrecargados, y yo los aliviaré. Pónganse bajo mi yugo y aprendan de mí, porque soy apacible y humilde de corazón. Conmigo encontrarán alivio. Porque mi yugo es fácil de llevar y mi carga pesa poco."
        ]
      },
      {
        "description": "Una mujer pecadora derrama aceite sobre los pies de Jesús",
        "timeStart": "00:18:56.64",
        "timeEnd": "00:25:49.51",
        "references": "Lucas 7:36-50",
        "refs": [
          {
            "label": "Lu 7:36-50",
            "tv": "42007036-42007050",
            "href": "/es/biblioteca/biblia/biblia-estudio/libros/lucas/7/#v42007036-v42007050"
          }
        ],
        "paragraphs": [
          "Ahora bien, uno de los fariseos insistía en invitarlo a comer con él. Así que Jesús entró en la casa del fariseo y se sentó a la mesa. Y sucedió que una mujer que era conocida en la ciudad como pecadora se enteró de que él estaba comiendo en casa del fariseo y trajo un frasco de alabastro lleno de aceite perfumado.",
          "Se puso detrás de él, llorando junto a sus pies, y comenzó a mojárselos con sus lágrimas y a secárselos con su cabello.",
          "También le besaba los pies tiernamente, y derramó el aceite perfumado sobre ellos.",
          "Al ver esto, el fariseo que lo había invitado se dijo a sí mismo: Si este hombre fuera realmente un profeta, sabría quién lo está tocando; sabría qué clase de mujer es: una pecadora.",
          "Simón, tengo algo que decirte.",
          "¡Dime, Maestro!",
          "Dos hombres le debían dinero a un prestamista; uno le debía 500 denarios, y el otro, 50.",
          "Como no tenían con qué pagarle, los perdonó generosamente a los dos. Entonces, ¿cuál de ellos lo amará más?",
          "Supongo que el hombre al que le perdonó más.",
          "Contestaste bien.",
          "¿Ves a esta mujer?",
          "Entré en tu casa y no me diste agua para los pies, pero esta mujer me ha mojado los pies con sus lágrimas y me los ha secado con su cabello. No me diste un beso, pero esta mujer, desde el momento en que entré, no ha dejado de besarme los pies tiernamente. No me pusiste aceite en la cabeza, pero esta mujer derramó aceite perfumado sobre mis pies.",
          "Por esta razón te digo que los pecados de ella, aunque son muchos, quedan perdonados, porque amó mucho.",
          "Pero, a quien se le perdona poco, ese ama poco.",
          "Tus pecados quedan perdonados.",
          "¿Quién es este hombre que hasta perdona pecados?",
          "Tu fe te ha salvado.",
          "Vete en paz."
        ]
      },
      {
        "description": "Algunas mujeres acompañan a Jesús",
        "timeStart": "00:25:50.84",
        "timeEnd": "00:27:23.43",
        "references": "Lucas 8:1-3",
        "refs": [
          {
            "label": "Lu 8:1-3",
            "tv": "42008001-42008003",
            "href": "/es/biblioteca/biblia/biblia-estudio/libros/lucas/8/#v42008001-v42008003"
          }
        ],
        "paragraphs": [
          "Poco después, él fue de ciudad en ciudad y de aldea en aldea predicando y anunciando las buenas noticias del Reino de Dios. Con él iban los Doce, así como ciertas mujeres que habían sido curadas de espíritus malvados y de enfermedades: María, a quien llamaban Magdalena",
          "—de quien habían salido siete demonios—, Juana la esposa de Cuza",
          "—el encargado de la casa de Herodes—, Susana y muchas otras mujeres que usaban sus bienes para atenderlos."
        ]
      },
      {
        "description": "Expulsa demonios por medio del espíritu santo, no por medio de Belcebú",
        "timeStart": "00:27:24.81",
        "timeEnd": "00:30:12.35",
        "references": "Mateo 12:22-30; Marcos 3:19b, 20",
        "refs": [
          {
            "label": "Mt 12:22-30;",
            "tv": "40012022-40012030",
            "href": "/es/biblioteca/biblia/biblia-estudio/libros/mateo/12/#v40012022-v40012030"
          },
          {
            "label": "Mr 3:19b, 20",
            "tv": "41003019-41003020",
            "href": "/es/biblioteca/biblia/biblia-estudio/libros/marcos/3/#v41003019-v41003020"
          }
        ],
        "paragraphs": [
          "Después Jesús entró en una casa, y una vez más se reunió tal multitud que ellos ni siquiera podían comer.",
          "Entonces le trajeron a un endemoniado que estaba ciego y mudo.",
          "Y Jesús lo curó, de manera que el mudo pudo hablar y ver. Todas las multitudes quedaron impactadas.",
          "¿No será este el Hijo de David?",
          "Este expulsa a los demonios por medio de Belcebú, el gobernante de los demonios. Sabiendo lo que pensaban, él les dijo: Todo reino dividido internamente va a la ruina y ninguna ciudad o familia dividida internamente se mantendrá en pie.",
          "De la misma manera, si Satanás expulsa a Satanás, está dividido internamente. ¿Cómo podrá su reino seguir en pie? Además, si yo expulso a los demonios por medio de Belcebú, ¿por medio de quién los expulsan los hijos de ustedes? Por eso ellos mismos los juzgarán a ustedes. Pero, si yo expulso a los demonios por medio del espíritu de Dios, es que el Reino de Dios los ha tomado a ustedes desprevenidos. Además, si alguien quiere invadir la casa de un hombre fuerte y robarle sus cosas, primero tiene que atar al hombre, ¿no les parece? Solo entonces le podrá saquear la casa.",
          "El que no está conmigo está contra mí, y el que no recoge conmigo desparrama."
        ]
      },
      {
        "description": "El pecado imperdonable",
        "timeStart": "00:30:12.85",
        "timeEnd": "00:30:52.48",
        "references": "Mateo 12:31, 32; Marcos 3:22-30",
        "refs": [
          {
            "label": "Mt 12:31, 32;",
            "tv": "40012031-40012032",
            "href": "/es/biblioteca/biblia/biblia-estudio/libros/mateo/12/#v40012031-v40012032"
          },
          {
            "label": "Mr 3:22-30",
            "tv": "41003022-41003030",
            "href": "/es/biblioteca/biblia/biblia-estudio/libros/marcos/3/#v41003022-v41003030"
          }
        ],
        "paragraphs": [
          "Por eso les digo que a los hombres se les perdonará todo tipo de pecado y blasfemia, pero la blasfemia contra el espíritu no se les perdonará. Por ejemplo, al que diga algo contra el Hijo del Hombre, su pecado se le perdonará; pero al que hable contra el espíritu santo no se le perdonará, no, ni en este sistema ni en el que va a venir."
        ]
      },
      {
        "description": "Se conoce el árbol por su fruto",
        "timeStart": "00:30:54.77",
        "timeEnd": "00:31:56.83",
        "references": "Mateo 12:33-37",
        "refs": [
          {
            "label": "Mt 12:33-37",
            "tv": "40012033-40012037",
            "href": "/es/biblioteca/biblia/biblia-estudio/libros/mateo/12/#v40012033-v40012037"
          }
        ],
        "paragraphs": [
          "O hacen que sea un árbol bueno y su fruto bueno, o hacen que sea un árbol podrido y su fruto podrido. Porque el árbol se conoce por su fruto.",
          "Crías de víboras, ¿cómo pueden hablar cosas buenas si son malos? Porque la boca habla de lo que abunda en el corazón. La persona buena saca cosas buenas de su tesoro de bondad; mientras que la persona mala saca cosas malas de su tesoro de maldad. Les digo que en el Día del Juicio la gente tendrá que dar cuenta de cualquier cosa inútil que diga. Porque por tus palabras serás declarado justo y por tus palabras serás condenado."
        ]
      },
      {
        "description": "La señal de Jonás",
        "timeStart": "00:31:59.96",
        "timeEnd": "00:33:26.42",
        "references": "Mateo 12:38-42",
        "refs": [
          {
            "label": "Mt 12:38-42",
            "tv": "40012038-40012042",
            "href": "/es/biblioteca/biblia/biblia-estudio/libros/mateo/12/#v40012038-v40012042"
          }
        ],
        "paragraphs": [
          "Maestro, queremos que nos des una señal.",
          "Esta generación infiel y malvada siempre anda buscando una señal.",
          "Pero no se le dará ninguna excepto la señal de Jonás el profeta. Porque, así como Jonás estuvo en el vientre del gran pez tres días y tres noches, el Hijo del Hombre estará en el corazón de la tierra tres días y tres noches.",
          "En el juicio, los habitantes de Nínive se levantarán con esta generación y la condenarán. Porque ellos se arrepintieron al escuchar lo que Jonás predicó. Pero, fíjense, aquí tienen a alguien que es más que Jonás. Y, en el juicio, la reina del sur se levantará con esta generación y la condenará. Porque ella vino desde el último rincón de la tierra para oír la sabiduría de Salomón. Pero, fíjense, aquí tienen a alguien que es más que Salomón."
        ]
      },
      {
        "description": "Cuando un demonio regresa a una persona",
        "timeStart": "00:33:27.05",
        "timeEnd": "00:34:37.41",
        "references": "Mateo 12:43-45",
        "refs": [
          {
            "label": "Mt 12:43-45",
            "tv": "40012043-40012045",
            "href": "/es/biblioteca/biblia/biblia-estudio/libros/mateo/12/#v40012043-v40012045"
          }
        ],
        "paragraphs": [
          "Cuando un espíritu maligno sale de una persona, pasa por lugares resecos buscando un sitio donde descansar, pero no lo encuentra.",
          "Entonces dice: “Volveré a mi casa, de la que me fui”.",
          "Y al llegar la encuentra desocupada, barrida y decorada. Entonces se va y lleva a otros siete espíritus todavía peores que él y, después de meterse dentro, se quedan allí. Y la situación final de la persona resulta peor que la primera.",
          "Eso es lo que le pasará a esta generación malvada."
        ]
      },
      {
        "description": "La madre y los hermanos de Jesús",
        "timeStart": "00:34:42.41",
        "timeEnd": "00:36:12.75",
        "references": "Mateo 12:46-50; Marcos 3:21, 31-35; Lucas 8:19-21",
        "refs": [
          {
            "label": "Mt 12:46-50;",
            "tv": "40012046-40012050",
            "href": "/es/biblioteca/biblia/biblia-estudio/libros/mateo/12/#v40012046-v40012050"
          },
          {
            "label": "Mr 3:21,",
            "tv": "41003021",
            "href": "/es/biblioteca/biblia/biblia-estudio/libros/marcos/3/#v41003021"
          },
          {
            "label": "31-35;",
            "tv": "41003031-41003035",
            "href": "/es/biblioteca/biblia/biblia-estudio/libros/marcos/3/#v41003031-v41003035"
          },
          {
            "label": "Lu 8:19-21",
            "tv": "42008019-42008021",
            "href": "/es/biblioteca/biblia/biblia-estudio/libros/lucas/8/#v42008019-v42008021"
          }
        ],
        "paragraphs": [
          "Cuando su familia se enteró de lo que estaba pasando, fueron a buscarlo para llevárselo, pues decían: “Se ha vuelto loco”.",
          "Mira, tu madre y tus hermanos están de pie afuera y quieren hablar contigo.",
          "¿Quién es mi madre, y quiénes son mis hermanos?",
          "¡Mira! ¡Estos son mi madre y mis hermanos! Porque todo el que hace la voluntad de mi Padre que está en el cielo es mi hermano y mi hermana y mi madre."
        ]
      },
      {
        "description": "Jesús habla a las multitudes desde una barca",
        "timeStart": "00:36:13.67",
        "timeEnd": "00:36:34.03",
        "references": "Mateo 13:1, 2; Marcos 4:1, 2; Lucas 8:4",
        "refs": [
          {
            "label": "Mt 13:1, 2;",
            "tv": "40013001-40013002",
            "href": "/es/biblioteca/biblia/biblia-estudio/libros/mateo/13/#v40013001-v40013002"
          },
          {
            "label": "Mr 4:1, 2;",
            "tv": "41004001-41004002",
            "href": "/es/biblioteca/biblia/biblia-estudio/libros/marcos/4/#v41004001-v41004002"
          },
          {
            "label": "Lu 8:4",
            "tv": "42008004",
            "href": "/es/biblioteca/biblia/biblia-estudio/libros/lucas/8/#v42008004"
          }
        ],
        "paragraphs": [
          "Aquel día, Jesús salió de la casa y se sentó a la orilla del mar.",
          "Y las multitudes que llegaron eran tan grandes que él se subió a una barca y se sentó, mientras toda la multitud estaba de pie en la playa."
        ]
      },
      {
        "description": "Semillas que caen en cuatro diferentes tipos de terreno",
        "timeStart": "00:36:35.57",
        "timeEnd": "00:37:55.69",
        "references": "Mateo 13:3-9; Marcos 4:3-9; Lucas 8:5-8",
        "refs": [
          {
            "label": "Mt 13:3-9;",
            "tv": "40013003-40013009",
            "href": "/es/biblioteca/biblia/biblia-estudio/libros/mateo/13/#v40013003-v40013009"
          },
          {
            "label": "Mr 4:3-9;",
            "tv": "41004003-41004009",
            "href": "/es/biblioteca/biblia/biblia-estudio/libros/marcos/4/#v41004003-v41004009"
          },
          {
            "label": "Lu 8:5-8",
            "tv": "42008005-42008008",
            "href": "/es/biblioteca/biblia/biblia-estudio/libros/lucas/8/#v42008005-v42008008"
          }
        ],
        "paragraphs": [
          "Entonces les enseñó muchas cosas usando comparaciones. ¡Escuchen! Un sembrador salió a sembrar. Y, al ir sembrando, algunas semillas cayeron junto al camino, y vinieron las aves y se las comieron. Otras cayeron en terreno rocoso, donde había poca tierra, y brotaron enseguida porque la tierra no tenía profundidad. Pero, cuando salió el sol, las plantas se quemaron y se marchitaron porque tenían pocas raíces. Otras cayeron entre espinos, y los espinos crecieron y las ahogaron. Y otras cayeron en la tierra buena y empezaron a dar fruto: unas dieron 100 veces más de lo que se había sembrado; otras 60, y otras 30. El que tenga oídos, que escuche con atención."
        ]
      },
      {
        "description": "Por qué Jesús enseña usando comparaciones",
        "timeStart": "00:38:00.74",
        "timeEnd": "00:40:49.45",
        "references": "Mateo 13:10-17; Marcos 4:10-13; Lucas 8:9, 10",
        "refs": [
          {
            "label": "Mt 13:10-17;",
            "tv": "40013010-40013017",
            "href": "/es/biblioteca/biblia/biblia-estudio/libros/mateo/13/#v40013010-v40013017"
          },
          {
            "label": "Mr 4:10-13;",
            "tv": "41004010-41004013",
            "href": "/es/biblioteca/biblia/biblia-estudio/libros/marcos/4/#v41004010-v41004013"
          },
          {
            "label": "Lu 8:9, 10",
            "tv": "42008009-42008010",
            "href": "/es/biblioteca/biblia/biblia-estudio/libros/lucas/8/#v42008009-v42008010"
          }
        ],
        "paragraphs": [
          "De modo que los discípulos se acercaron y le preguntaron: ¿Por qué les hablas usando comparaciones?",
          "A ustedes se les concede entender los secretos sagrados del Reino de los cielos, pero a ellos no. Porque al que tiene se le dará más, y tendrá en abundancia; pero al que no tiene se le quitará hasta lo que tiene.",
          "Por eso les hablo a ellos usando comparaciones.",
          "Aunque ven, en realidad no ven y, aunque oyen, no oyen ni tampoco comprenden nada.",
          "En ellos se cumple esta profecía de Isaías: “Ustedes van a oír, pero jamás van a comprender. Van a mirar, pero jamás van a ver.",
          "Porque el corazón de este pueblo se ha hecho insensible.",
          "Se han tapado los oídos y han cerrado los ojos, para que nunca vean con los ojos ni oigan con los oídos ni comprendan con el corazón ni regresen a Dios y yo los sane”.",
          "Sin embargo, felices los ojos de ustedes, que ven, y sus oídos, que oyen. Porque les aseguro que muchos profetas y personas justas desearon ver las cosas que ustedes están observando, pero no las vieron, y oír las cosas que ustedes están oyendo, pero no las oyeron."
        ]
      },
      {
        "description": "Explicación de la parábola del sembrador",
        "timeStart": "00:40:49.86",
        "timeEnd": "00:42:25.21",
        "references": "Mateo 13:18-23; Marcos 4:14-29; Lucas 8:11-18",
        "refs": [
          {
            "label": "Mt 13:18-23;",
            "tv": "40013018-40013023",
            "href": "/es/biblioteca/biblia/biblia-estudio/libros/mateo/13/#v40013018-v40013023"
          },
          {
            "label": "Mr 4:14-29;",
            "tv": "41004014-41004029",
            "href": "/es/biblioteca/biblia/biblia-estudio/libros/marcos/4/#v41004014-v41004029"
          },
          {
            "label": "Lu 8:11-18",
            "tv": "42008011-42008018",
            "href": "/es/biblioteca/biblia/biblia-estudio/libros/lucas/8/#v42008011-v42008018"
          }
        ],
        "paragraphs": [
          "Así que ahora escuchen lo que significa el ejemplo del sembrador.",
          "Cuando alguien oye la palabra del Reino pero no la comprende, el Maligno viene y arranca lo que se sembró en su corazón.",
          "Esta es la semilla que se sembró junto al camino. La semilla que se sembró en terreno rocoso es el que oye la palabra y enseguida la acepta con alegría. Pero no tiene raíces profundas en su interior y solo sigue adelante por un tiempo. Cuando surgen dificultades o persecución por causa de la palabra, enseguida tropieza. La semilla que se sembró entre los espinos es el que oye la palabra pero deja que las preocupaciones de este sistema y el poder engañoso de las riquezas la ahoguen, y por eso la palabra no da fruto. Y la semilla que se sembró en la tierra buena son los que oyen la palabra y comprenden su significado. Estos sí dan fruto. Unos producen 100 veces más; otros 60, y otros 30."
        ]
      },
      {
        "description": "El trigo y la mala hierba",
        "timeStart": "00:42:26.71",
        "timeEnd": "00:43:46.21",
        "references": "Mateo 13:24-30",
        "refs": [
          {
            "label": "Mt 13:24-30",
            "tv": "40013024-40013030",
            "href": "/es/biblioteca/biblia/biblia-estudio/libros/mateo/13/#v40013024-v40013030"
          }
        ],
        "paragraphs": [
          "El Reino de los cielos puede compararse a un hombre que sembró en su campo buena semilla. Mientras los hombres dormían, vino su enemigo, sembró mala hierba entre el trigo y se fue. Cuando los tallos brotaron y aparecieron las espigas, también apareció la mala hierba. Así que los esclavos del señor de la casa vinieron y le dijeron: “Amo, ¿no sembraste buena semilla en tu campo? Entonces, ¿por qué hay mala hierba?”. Él les dijo: “Esto lo hizo un hombre, un enemigo”. Los esclavos le preguntaron: “¿Quieres que vayamos y la arranquemos?”. Él respondió: “No, no sea que al arrancar la mala hierba arranquen también el trigo. Dejen que crezcan juntos hasta la cosecha, y en la temporada de la cosecha les diré a los cosechadores que primero arranquen la mala hierba y la aten en manojos para quemarla y que luego recojan el trigo y lo guarden en mi granero”."
        ]
      },
      {
        "description": "El grano de mostaza; la levadura",
        "timeStart": "00:43:47.21",
        "timeEnd": "00:44:42.68",
        "references": "Mateo 13:31-33; Marcos 4:30-32",
        "refs": [
          {
            "label": "Mt 13:31-33;",
            "tv": "40013031-40013033",
            "href": "/es/biblioteca/biblia/biblia-estudio/libros/mateo/13/#v40013031-v40013033"
          },
          {
            "label": "Mr 4:30-32",
            "tv": "41004030-41004032",
            "href": "/es/biblioteca/biblia/biblia-estudio/libros/marcos/4/#v41004030-v41004032"
          }
        ],
        "paragraphs": [
          "El Reino de los cielos es como un grano de mostaza que un hombre tomó y sembró en su campo. Esta semilla es, sin duda, la más pequeña de todas las semillas, pero cuando crece es la más grande de todas las plantas de huerto y se convierte en un árbol, y así las aves del cielo vienen a refugiarse entre sus ramas.",
          "El Reino de los cielos es como la levadura que una mujer tomó y mezcló con tres grandes medidas de harina.",
          "Al final, toda la masa fermentó."
        ]
      },
      {
        "description": "Jesús usa comparaciones y cumple una profecía",
        "timeStart": "00:44:45.81",
        "timeEnd": "00:45:13.34",
        "references": "Mateo 13:34, 35; Marcos 4:33, 34",
        "refs": [
          {
            "label": "Mt 13:34, 35;",
            "tv": "40013034-40013035",
            "href": "/es/biblioteca/biblia/biblia-estudio/libros/mateo/13/#v40013034-v40013035"
          },
          {
            "label": "Mr 4:33, 34",
            "tv": "41004033-41004034",
            "href": "/es/biblioteca/biblia/biblia-estudio/libros/marcos/4/#v41004033-v41004034"
          }
        ],
        "paragraphs": [
          "Jesús les dijo todas estas cosas a las multitudes usando comparaciones.",
          "De hecho, nunca les hablaba sin utilizar alguna comparación. Así se cumplió lo que se había anunciado por medio del profeta, que dijo: “Abriré mi boca usando comparaciones; proclamaré cosas que han estado escondidas desde la fundación”."
        ]
      },
      {
        "description": "Explicación de la parábola del trigo y la mala hierba",
        "timeStart": "00:45:14.04",
        "timeEnd": "00:47:10.95",
        "references": "Mateo 13:36-43",
        "refs": [
          {
            "label": "Mt 13:36-43",
            "tv": "40013036-40013043",
            "href": "/es/biblioteca/biblia/biblia-estudio/libros/mateo/13/#v40013036-v40013043"
          }
        ],
        "paragraphs": [
          "Luego, después de despedir a las multitudes, entró en la casa.",
          "Sus discípulos se le acercaron y le dijeron: Explícanos el ejemplo de la mala hierba en el campo.",
          "El sembrador de la buena semilla es el Hijo del Hombre.",
          "El campo es el mundo. La buena semilla son los hijos del Reino. La mala hierba son los hijos del Maligno y el enemigo que la sembró es el Diablo. La cosecha es la conclusión de un sistema y los cosechadores son los ángeles. De manera que, así como se arranca la mala hierba y se quema en el fuego, así pasará en la conclusión del sistema. El Hijo del Hombre enviará a sus ángeles, y ellos sacarán de su Reino todas las cosas que llevan al pecado y a las personas que violan la ley, y las arrojarán en el horno de fuego. Ahí es donde llorarán y apretarán los dientes.",
          "En ese tiempo, los justos brillarán en el Reino de su Padre tanto como el sol.",
          "El que tenga oídos,"
        ]
      },
      {
        "description": "El tesoro escondido; la perla muy valiosa",
        "timeStart": "00:47:11.41",
        "timeEnd": "00:48:03.96",
        "references": "Mateo 13:44-46",
        "refs": [
          {
            "label": "Mt 13:44-46",
            "tv": "40013044-40013046",
            "href": "/es/biblioteca/biblia/biblia-estudio/libros/mateo/13/#v40013044-v40013046"
          }
        ],
        "paragraphs": [
          "que escuche con atención. El Reino de los cielos es como un tesoro que estaba escondido en un campo y que un hombre encontró. El hombre lo volvió a esconder y, de la alegría que le dio, fue y vendió todo lo que tenía y compró ese campo.",
          "El Reino de los cielos también es como un comerciante viajero que buscaba perlas finas.",
          "Al encontrar una perla muy valiosa, se fue y enseguida vendió todas las cosas que tenía y la compró."
        ]
      },
      {
        "description": "La red de pesca",
        "timeStart": "00:48:04.97",
        "timeEnd": "00:48:51.85",
        "references": "Mateo 13:47-50",
        "refs": [
          {
            "label": "Mt 13:47-50",
            "tv": "40013047-40013050",
            "href": "/es/biblioteca/biblia/biblia-estudio/libros/mateo/13/#v40013047-v40013050"
          }
        ],
        "paragraphs": [
          "El Reino de los cielos también es como una red de pesca que bajaron al mar y recogió peces de todo tipo. Cuando se llenó, la arrastraron hasta la playa, se sentaron y pusieron los peces buenos en recipientes, pero los que no servían los desecharon.",
          "Eso es lo que pasará en la conclusión del sistema.",
          "Los ángeles saldrán, separarán a los malvados de los justos y los echarán en el horno de fuego. Ahí es donde llorarán y apretarán los dientes."
        ]
      },
      {
        "description": "El maestro saca de su tesoro cosas nuevas y cosas viejas",
        "timeStart": "00:48:52.35",
        "timeEnd": "00:49:59.66",
        "references": "Mateo 13:51-53",
        "refs": [
          {
            "label": "Mt 13:51-53",
            "tv": "40013051-40013053",
            "href": "/es/biblioteca/biblia/biblia-estudio/libros/mateo/13/#v40013051-v40013053"
          }
        ],
        "paragraphs": [
          "¿Comprendieron el sentido de todo esto?",
          "— Sí. Sí. En ese caso, sepan esto: todo maestro que ha sido instruido acerca del Reino de los cielos es como un hombre, el señor de la casa, que saca de su tesoro cosas nuevas y cosas viejas.",
          "Después de ponerles estas comparaciones, Jesús se fue de allí."
        ]
      }
    ]
  }
]